simplemathutils_lib/__init__.py
simplemathutils_lib/class_simplemath.py
simplemathutils_lib/simplemath.py
tests/__init__.py
tests/simplemath_test.py
simplemathutils_lib-0.1.2.dist-info/LICENSE.txt
simplemathutils_lib-0.1.2.dist-info/METADATA
simplemathutils_lib-0.1.2.dist-info/WHEEL
simplemathutils_lib-0.1.2.dist-info/top_level.txt
simplemathutils_lib-0.1.2.dist-info/RECORD
