Metadata-Version: 2.1
Name: simplemathutils_lib
Version: 0.1.2
Summary: simplemathutils-lib is a creative package for basic mathematical operations with Python.
Home-page: https://github.com/MattithyahuData/simplemathutils-lib
Author: Mattithyahu O
Author-email: contactmattithyahu@gmail.com
License: UNKNOWN
Keywords: math
Platform: UNKNOWN
Classifier: Development Status :: 5 - Production/Stable
Classifier: Intended Audience :: Science/Research
Classifier: Intended Audience :: Developers
Classifier: License :: OSI Approved :: MIT License
Classifier: Programming Language :: Python :: 3
Classifier: Topic :: Software Development
Classifier: Topic :: Scientific/Engineering
Classifier: Typing :: Typed
Classifier: Operating System :: MacOS :: MacOS X
Classifier: Operating System :: Microsoft :: Windows
Requires-Python: >=3.6
License-File: LICENSE.txt
